voyage_embedders/__about__.py
voyage_embedders/__init__.py
voyage_embedders/voyage_document_embedder.py
voyage_embedders/voyage_text_embedder.py
voyage_embedders-1.0.0.dist-info/METADATA
voyage_embedders-1.0.0.dist-info/WHEEL
voyage_embedders-1.0.0.dist-info/licenses/LICENSE
voyage_embedders-1.0.0.dist-info/RECORD
