Metadata-Version: 2.1
Name: voyage_embedders
Version: 1.0.0
Project-URL: Documentation, https://github.com/awinml/voyage-embedders-haystack#readme
Project-URL: Issues, https://github.com/awinml/voyage-embedders-haystack/issues
Project-URL: Source, https://github.com/awinml/voyage-embedders-haystack
Author: Ashwin Mathur
License-Expression: Apache-2.0
License-File: LICENSE
Keywords: haystack,voyage_embedders,voyageai
Classifier: Development Status :: 4 - Beta
Classifier: Programming Language :: Python
Classifier: Programming Language :: Python :: 3.7
Classifier: Programming Language :: Python :: 3.8
Classifier: Programming Language :: Python :: 3.9
Classifier: Programming Language :: Python :: 3.10
Classifier: Programming Language :: Python :: 3.11
Classifier: Programming Language :: Python :: Implementation :: CPython
Classifier: Programming Language :: Python :: Implementation :: PyPy
Requires-Python: >=3.7
Requires-Dist: haystack-ai
Requires-Dist: numpy
Requires-Dist: typing-extensions
Requires-Dist: voyageai
